k_sequencing/__init__.py
k_sequencing/connector.py
k_sequencing/errors.py
k_sequencing/responses.py
k_sequencing-0.1.0.dist-info/DESCRIPTION.rst
k_sequencing-0.1.0.dist-info/METADATA
k_sequencing-0.1.0.dist-info/RECORD
k_sequencing-0.1.0.dist-info/WHEEL
k_sequencing-0.1.0.dist-info/metadata.json
k_sequencing-0.1.0.dist-info/top_level.txt
