Metadata-Version: 2.0
Name: k-sequencing
Version: 0.1.0
Summary: k-sequencing client for python user
Home-page: https://datawow.io
Author: Datawow.io
Author-email: info@datawow.io
License: MIT
Platform: UNKNOWN
Classifier: License :: OSI Approved :: MIT License
Classifier: Operating System :: OS Independent
Classifier: Programming Language :: Python
Classifier: Programming Language :: Python :: 2
Classifier: Programming Language :: Python :: 2.7
Requires-Dist: requests
Requires-Dist: mock (>=2.0.0)
